{"comment": "{\n    \"VARIABLES\": \"Let x1 be the number of hours factory 1 operates (integer), and x2 be the number of hours factory 2 operates (integer).\",\n    \"CONSTRAINTS\": {\n        \"Factory 1 production constraints - Black Bears\": \"5x1 + 10x2 \\geq 20\",\n        \"Factory 1 production constraints - White Bears\": \"6x1 + 10x2 \\geq 5\",\n        \"Factory 1 production constraints - Brown Bears\": \"3x1 \\geq 15\",\n        \"Non-negativity constraints\": \"x1, x2 \\geq 0\"\n    },\n    \"OBJECTIVE\": \"Minimize the total cost: $300x1 + $600x2\"\n}", "expert": "Modeling Expert"}