{"comment": "{\n    \"VARIABLES\": \"Let x1 be the number of hours factory 1 operates (integer), and x2 be the number of hours factory 2 operates (integer). Both x1 and x2 are non-negative integers.\",\n    \"CONSTRAINS\": {\n        \"Factory 1 production constraints\": \"5x1 + 10x2 \\geq 20 (black bears)\",\n        \"Factory 2 production constraints\": \"6x1 + 10x2 \\geq 5 (white bears)\",\n        \"Factory 1 production constraints\": \"3x1 \\geq 15 (brown bears)\"\n    },\n    \"OBJECTIVE\": \"Minimize the total cost: $300x1 + $600x2\"\n}", "expert": "Modeling Expert"}